wrapperpackage/__init__.py
wrapperpackage/wrapperfunctest.py
wrapperpackage-0.0.1.dist-info/Licence.txt
wrapperpackage-0.0.1.dist-info/METADATA
wrapperpackage-0.0.1.dist-info/WHEEL
wrapperpackage-0.0.1.dist-info/top_level.txt
wrapperpackage-0.0.1.dist-info/RECORD
